<?xml version="1.0" encoding="UTF-8" standalone="yes"?>
<AssignMessage async="false" continueOnError="false" enabled="true" name="am_capturebinguri">
    <DisplayName>AM_CaptureBingURI</DisplayName>
    <FaultRules/>
    <Properties/>
    <AssignVariable>
        <Name>bingURI</Name>
        <Value/>
      <Ref>request.uri</Ref>
    </AssignVariable>
    <IgnoreUnresolvedVariables>true</IgnoreUnresolvedVariables>
    <AssignTo createNew="false" transport="http" type="request"/>
</AssignMessage>
